{"嘉定":[{"id":"101020500","l":3,"parent":"上海","name":"嘉定"}],"金山":[{"id":"101020700","l":3,"parent":"上海","name":"金山"}],"津南":[{"id":"101031000","l":3,"parent":"天津","name":"津南"}],"蓟县":[{"id":"101031400","l":3,"parent":"天津","name":"蓟县"}],"静海":[{"id":"101030900","l":3,"parent":"天津","name":"静海"}],"江津":[{"id":"101040500","l":3,"parent":"重庆","name":"江津"}],"鸡西":[{"id":"101051101","l":2,"parent":"黑龙江","name":"鸡西"}],"鸡东":[{"id":"101051104","l":3,"parent":"黑龙江-鸡西","name":"鸡东"}],"集贤":[{"id":"101051302","l":3,"parent":"黑龙江-双鸭山","name":"集贤"}],"佳木斯":[{"id":"101050401","l":2,"parent":"黑龙江","name":"佳木斯"}],"加格达奇":[{"id":"101050708","l":3,"parent":"黑龙江-大兴安岭","name":"加格达奇"}],"嘉荫":[{"id":"101050805","l":3,"parent":"黑龙江-伊春","name":"嘉荫"}],"吉林":[{"id":"101060101","l":1,"name":"吉林"},{"id":"101060201","l":2,"parent":"吉林","name":"吉林"}],"九台":[{"id":"101060104","l":3,"parent":"吉林-长春","name":"九台"}],"蛟河":[{"id":"101060204","l":3,"parent":"吉林-吉林","name":"蛟河"}],"集安":[{"id":"101060505","l":2,"parent":"吉林","name":"集安"}],"靖宇":[{"id":"101060902","l":3,"parent":"吉林-白山","name":"靖宇"}],"江源":[{"id":"101060907","l":3,"parent":"吉林-白山","name":"江源"}],"建平县":[{"id":"101071207","l":3,"parent":"辽宁-朝阳","name":"建平县"}],"建昌":[{"id":"101071402","l":3,"parent":"辽宁-葫芦岛","name":"建昌"}],"金州":[{"id":"101070203","l":3,"parent":"辽宁-大连","name":"金州"}],"锦州":[{"id":"101070701","l":2,"parent":"辽宁","name":"锦州"}],"吉兰太":[{"id":"101081205","l":3,"parent":"内蒙古-阿拉善盟","name":"吉兰太"}],"集宁":[{"id":"101080401","l":3,"parent":"内蒙古-乌兰察布","name":"集宁"}],"鸡泽":[{"id":"101091011","l":3,"parent":"河北-邯郸","name":"鸡泽"}],"晋州":[{"id":"101090116","l":3,"parent":"河北-石家庄","name":"晋州"}],"井陉":[{"id":"101090102","l":3,"parent":"河北-石家庄","name":"井陉"}],"冀州":[{"id":"101090810","l":3,"parent":"河北-衡水","name":"冀州"}],"景县":[{"id":"101090808","l":2,"parent":"河北","name":"景县"}],"巨鹿":[{"id":"101090909","l":2,"parent":"河北","name":"巨鹿"}],"静乐":[{"id":"101101012","l":3,"parent":"山西-忻州","name":"静乐"}],"交城":[{"id":"101101113","l":3,"parent":"山西-吕梁","name":"交城"}],"交口":[{"id":"101101108","l":3,"parent":"山西-吕梁","name":"交口"}],"尖草坪区":[{"id":"101100106","l":3,"parent":"山西-太原","name":"尖草坪区"}],"介休":[{"id":"101100412","l":3,"parent":"山西-晋中","name":"介休"}],"晋中":[{"id":"101100401","l":2,"parent":"山西","name":"晋中"}],"晋城":[{"id":"101100601","l":2,"parent":"山西","name":"晋城"}],"吉县":[{"id":"101100706","l":3,"parent":"山西-临汾","name":"吉县"}],"稷山":[{"id":"101100803","l":3,"parent":"山西-运城","name":"稷山"}],"绛县":[{"id":"101100807","l":3,"parent":"山西-运城","name":"绛县"}],"泾阳":[{"id":"101110205","l":3,"parent":"陕西-咸阳","name":"泾阳"}],"佳县":[{"id":"101110404","l":2,"parent":"陕西","name":"佳县"}],"靖边":[{"id":"101110406","l":3,"parent":"陕西-榆林","name":"靖边"}],"鄄城":[{"id":"101121002","l":3,"parent":"山东-菏泽","name":"鄄城"}],"巨野":[{"id":"101121006","l":3,"parent":"山东-菏泽","name":"巨野"}],"莒县":[{"id":"101121503","l":3,"parent":"山东-日照","name":"莒县"}],"济南":[{"id":"101120101","l":2,"parent":"山东","name":"济南"}],"济阳":[{"id":"101120106","l":3,"parent":"山东-济南","name":"济阳"}],"即墨":[{"id":"101120204","l":3,"parent":"山东-青岛","name":"即墨"}],"胶州":[{"id":"101120205","l":3,"parent":"山东-青岛","name":"胶州"}],"胶南":[{"id":"101120206","l":3,"parent":"山东-青岛","name":"胶南"}],"济宁":[{"id":"101120701","l":2,"parent":"山东","name":"济宁"}],"嘉祥":[{"id":"101120702","l":3,"parent":"山东-济宁","name":"嘉祥"}],"金乡":[{"id":"101120706","l":3,"parent":"山东-济宁","name":"金乡"}],"莒南":[{"id":"101120902","l":3,"parent":"山东-临沂","name":"莒南"}],"吉木乃":[{"id":"101131405","l":3,"parent":"新疆-阿勒泰","name":"吉木乃"}],"精河":[{"id":"101131603","l":3,"parent":"新疆-博州","name":"精河"}],"吉木萨尔":[{"id":"101130405","l":3,"parent":"新疆-昌吉","name":"吉木萨尔"}],"吉隆":[{"id":"101140210","l":3,"parent":"西藏-日喀则","name":"吉隆"}],"江孜":[{"id":"101140206","l":3,"parent":"西藏-日喀则","name":"江孜"}],"加查":[{"id":"101140304","l":3,"parent":"西藏-山南","name":"加查"}],"江达":[{"id":"101140509","l":3,"parent":"西藏-昌都","name":"江达"}],"嘉黎":[{"id":"101140603","l":3,"parent":"西藏-那曲","name":"嘉黎"}],"尖扎":[{"id":"101150302","l":3,"parent":"青海-黄南","name":"尖扎"}],"久治":[{"id":"101150505","l":2,"parent":"青海","name":"久治"}],"积石山":[{"id":"101161107","l":3,"parent":"甘肃-临夏","name":"积石山"}],"靖远":[{"id":"101161302","l":3,"parent":"甘肃-白银","name":"靖远"}],"景泰":[{"id":"101161305","l":3,"parent":"甘肃-白银","name":"景泰"}],"嘉峪关":[{"id":"101161401","l":2,"parent":"甘肃","name":"嘉峪关"}],"泾川":[{"id":"101160302","l":3,"parent":"甘肃-平凉","name":"泾川"}],"静宁":[{"id":"101160307","l":3,"parent":"甘肃-平凉","name":"静宁"}],"金昌":[{"id":"101160601","l":2,"parent":"甘肃","name":"金昌"}],"酒泉":[{"id":"101160801","l":2,"parent":"甘肃","name":"酒泉"}],"金塔":[{"id":"101160803","l":3,"parent":"甘肃-酒泉","name":"金塔"}],"泾源":[{"id":"101170404","l":2,"parent":"宁夏","name":"泾源"}],"焦作":[{"id":"101181101","l":2,"parent":"河南","name":"焦作"}],"济源":[{"id":"101181801","l":2,"parent":"河南","name":"济源"}],"郏县":[{"id":"101180502","l":3,"parent":"河南-平顶山","name":"郏县"}],"吉利":[{"id":"101180911","l":3,"parent":"河南-洛阳","name":"吉利"}],"金坛":[{"id":"101191103","l":3,"parent":"江苏-常州","name":"金坛"}],"姜堰":[{"id":"101191204","l":3,"parent":"江苏-泰州","name":"姜堰"}],"靖江":[{"id":"101191205","l":3,"parent":"江苏-泰州","name":"靖江"}],"江苏":[{"id":"101190101","l":1,"name":"江苏"}],"江宁":[{"id":"101190104","l":3,"parent":"江苏-南京","name":"江宁"}],"江浦":[{"id":"101190106","l":3,"parent":"江苏-南京","name":"江浦"}],"江阴":[{"id":"101190202","l":2,"parent":"江苏","name":"江阴"}],"江都":[{"id":"101190605","l":3,"parent":"江苏-扬州","name":"江都"}],"建湖":[{"id":"101190706","l":3,"parent":"江苏-盐城","name":"建湖"}],"金湖":[{"id":"101190902","l":3,"parent":"江苏-淮安","name":"金湖"}],"建始":[{"id":"101201003","l":3,"parent":"湖北-恩施","name":"建始"}],"荆门":[{"id":"101201401","l":2,"parent":"湖北","name":"荆门"}],"京山":[{"id":"101201403","l":3,"parent":"湖北-荆门","name":"京山"}],"江夏":[{"id":"101200105","l":3,"parent":"湖北-武汉","name":"江夏"}],"嘉鱼":[{"id":"101200703","l":3,"parent":"湖北-咸宁","name":"嘉鱼"}],"荆州":[{"id":"101200801","l":2,"parent":"湖北","name":"荆州"}],"江陵":[{"id":"101200802","l":3,"parent":"湖北-荆州","name":"江陵"}],"监利":[{"id":"101200805","l":3,"parent":"湖北-荆州","name":"监利"}],"江山":[{"id":"101211005","l":3,"parent":"浙江-衢州","name":"江山"}],"建德":[{"id":"101210105","l":3,"parent":"浙江-杭州","name":"建德"}],"嘉兴":[{"id":"101210301","l":2,"parent":"浙江","name":"嘉兴"}],"嘉善":[{"id":"101210302","l":3,"parent":"浙江-嘉兴","name":"嘉善"}],"椒江":[{"id":"101210611","l":3,"parent":"浙江-台州","name":"椒江"}],"缙云":[{"id":"101210804","l":3,"parent":"浙江-丽水","name":"缙云"}],"景宁":[{"id":"101210809","l":3,"parent":"浙江-丽水","name":"景宁"}],"金华":[{"id":"101210901","l":2,"parent":"浙江","name":"金华"}],"泾县":[{"id":"101221402","l":3,"parent":"安徽-宣城","name":"泾县"}],"旌德":[{"id":"101221403","l":3,"parent":"安徽-宣城","name":"旌德"}],"绩溪":[{"id":"101221405","l":3,"parent":"安徽-宣城","name":"绩溪"}],"金寨":[{"id":"101221505","l":3,"parent":"安徽-六安","name":"金寨"}],"九华山":[{"id":"101221704","l":3,"parent":"安徽-池州","name":"九华山"}],"界首":[{"id":"101220805","l":3,"parent":"安徽-阜阳","name":"界首"}],"晋江":[{"id":"101230509","l":3,"parent":"福建-泉州","name":"晋江"}],"建宁":[{"id":"101230806","l":3,"parent":"福建-三明","name":"建宁"}],"建瓯":[{"id":"101230910","l":3,"parent":"福建-南平","name":"建瓯"}],"建阳":[{"id":"101230907","l":3,"parent":"福建-南平","name":"建阳"}],"江西":[{"id":"101240101","l":1,"name":"江西"}],"进贤":[{"id":"101240105","l":3,"parent":"江西-南昌","name":"进贤"}],"九江":[{"id":"101240201","l":2,"parent":"江西","name":"九江"}],"金溪":[{"id":"101240405","l":3,"parent":"江西-抚州","name":"金溪"}],"靖安":[{"id":"101240506","l":3,"parent":"江西-宜春","name":"靖安"}],"吉安":[{"id":"101240601","l":2,"parent":"江西","name":"吉安"}],"吉安县":[{"id":"101240602","l":3,"parent":"江西-吉安","name":"吉安县"}],"吉水":[{"id":"101240603","l":3,"parent":"江西-吉安","name":"吉水"}],"井冈山":[{"id":"101240608","l":3,"parent":"江西-吉安","name":"井冈山"}],"景德镇":[{"id":"101240801","l":2,"parent":"江西","name":"景德镇"}],"靖州":[{"id":"101251205","l":3,"parent":"湖南-怀化","name":"靖州"}],"江华":[{"id":"101251410","l":3,"parent":"湖南-永州","name":"江华"}],"江永":[{"id":"101251407","l":3,"parent":"湖南-永州","name":"江永"}],"吉首":[{"id":"101251501","l":3,"parent":"湖南-湘西","name":"吉首"}],"嘉禾":[{"id":"101250503","l":3,"parent":"湖南-郴州","name":"嘉禾"}],"津市":[{"id":"101250608","l":3,"parent":"湖南-常德","name":"津市"}],"剑河":[{"id":"101260511","l":3,"parent":"贵州-黔东南","name":"剑河"}],"锦屏":[{"id":"101260515","l":3,"parent":"贵州-黔东南","name":"锦屏"}],"江口":[{"id":"101260602","l":3,"parent":"贵州-铜仁","name":"江口"}],"金沙":[{"id":"101260703","l":3,"parent":"贵州-毕节","name":"金沙"}],"江安":[{"id":"101271105","l":3,"parent":"四川-宜宾","name":"江安"}],"简阳":[{"id":"101271304","l":3,"parent":"四川-资阳","name":"简阳"}],"井研":[{"id":"101271403","l":3,"parent":"四川-乐山","name":"井研"}],"金阳":[{"id":"101271611","l":3,"parent":"四川-凉山","name":"金阳"}],"九龙":[{"id":"101271805","l":3,"parent":"四川-甘孜","name":"九龙"},{"id":"101320102","l":3,"parent":"香港-香港","name":"九龙"}],"九寨沟":[{"id":"101271906","l":3,"parent":"四川-阿坝","name":"九寨沟"}],"金川":[{"id":"101271907","l":3,"parent":"四川-阿坝","name":"金川"}],"剑阁":[{"id":"101272104","l":3,"parent":"四川-广元","name":"剑阁"}],"金堂":[{"id":"101270105","l":3,"parent":"四川-成都","name":"金堂"}],"江油":[{"id":"101270408","l":3,"parent":"四川-绵阳","name":"江油"}],"江门":[{"id":"101281101","l":2,"parent":"广东","name":"江门"}],"江海":[{"id":"101281109","l":3,"parent":"广东-江门","name":"江海"}],"揭阳":[{"id":"101281901","l":2,"parent":"广东","name":"揭阳"}],"揭西":[{"id":"101281902","l":3,"parent":"广东-揭阳","name":"揭西"}],"揭东":[{"id":"101281905","l":3,"parent":"广东-揭阳","name":"揭东"}],"金湾":[{"id":"101280703","l":3,"parent":"广东-珠海","name":"金湾"}],"景洪":[{"id":"101291601","l":3,"parent":"云南-西双版纳","name":"景洪"}],"晋宁":[{"id":"101290105","l":3,"parent":"云南-昆明","name":"晋宁"}],"剑川":[{"id":"101290209","l":3,"parent":"云南-大理","name":"剑川"}],"金平":[{"id":"101290312","l":3,"parent":"云南-红河","name":"金平"}],"建水":[{"id":"101290303","l":2,"parent":"云南","name":"建水"}],"江川":[{"id":"101290703","l":3,"parent":"云南-玉溪","name":"江川"}],"景谷":[{"id":"101290902","l":3,"parent":"云南-普洱","name":"景谷"}],"景东":[{"id":"101290903","l":3,"parent":"云南-普洱","name":"景东"}],"江城":[{"id":"101290907","l":3,"parent":"云南-普洱","name":"江城"}],"靖西":[{"id":"101301005","l":3,"parent":"广西-百色","name":"靖西"}],"金秀":[{"id":"101300403","l":3,"parent":"广西-来宾","name":"金秀"}],"嘉义":[{"id":"101340202","l":2,"parent":"台湾","name":"嘉义"}]}